easy_twitter_publisher/__init__.py
easy_twitter_publisher/twitter_publisher/__init__.py
easy_twitter_publisher/twitter_publisher/constants.py
easy_twitter_publisher/twitter_publisher/exceptions.py
easy_twitter_publisher/twitter_publisher/twitter_media.py
easy_twitter_publisher/twitter_publisher/twitter_post.py
easy_twitter_publisher/twitter_utils/__init__.py
easy_twitter_publisher/twitter_utils/twitter_utils.py
easy_twitter_publisher-1.0.3.dist-info/LICENSE
easy_twitter_publisher-1.0.3.dist-info/METADATA
easy_twitter_publisher-1.0.3.dist-info/WHEEL
easy_twitter_publisher-1.0.3.dist-info/top_level.txt
easy_twitter_publisher-1.0.3.dist-info/RECORD
