Metadata-Version: 2.1
Name: easy-twitter-publisher
Version: 1.0.3
Summary: 简易、好用的推特(Twitter)发帖/回帖程序,支持图片，视频
Home-page: https://easy-twitter-publisher.xink.top/
Author: hanxinkong
Author-email: xinkonghan@gmail.com
License: MIT
Keywords: easy,twitter,publisher
Requires-Python: >=3.6.8
License-File: LICENSE
Requires-Dist: easy-spider-tool (==1.0.7)
Requires-Dist: loguru (==0.7.0)
Requires-Dist: requests (==2.27.1)
Requires-Dist: urllib3 (==1.26.15)
Requires-Dist: requests-toolbelt (==1.0.0)
